opensarlab_notifications/__init__.py
opensarlab_notifications/_version.py
opensarlab_notifications/handlers.py
opensarlab_notifications/labextension/build_log.json
opensarlab_notifications/labextension/package.json
opensarlab_notifications/labextension/static/lib_index_js.d4b1b0325ea49aefeac5.js
opensarlab_notifications/labextension/static/lib_index_js.d4b1b0325ea49aefeac5.js.map
opensarlab_notifications/labextension/static/remoteEntry.674dd3eab28587a2593a.js
opensarlab_notifications/labextension/static/remoteEntry.674dd3eab28587a2593a.js.map
opensarlab_notifications/labextension/static/style.js
opensarlab_notifications/labextension/static/style_index_js.d38fb6999d226c36f186.js
opensarlab_notifications/labextension/static/style_index_js.d38fb6999d226c36f186.js.map
opensarlab_notifications/labextension/static/vendors-node_modules_css-loader_dist_runtime_api_js-node_modules_css-loader_dist_runtime_cssW-72eba1.766d91b9c4247d5d440e.js
opensarlab_notifications/labextension/static/vendors-node_modules_css-loader_dist_runtime_api_js-node_modules_css-loader_dist_runtime_cssW-72eba1.766d91b9c4247d5d440e.js.map
opensarlab_notifications/labextension/static/vendors-node_modules_jquery_dist_jquery_js.0f67f7a18699a0526af8.js
opensarlab_notifications/labextension/static/vendors-node_modules_jquery_dist_jquery_js.0f67f7a18699a0526af8.js.map
opensarlab_notifications/labextension/static/vendors-node_modules_toastr_toastr_js.39c3e89e462a0d392ed0.js
opensarlab_notifications/labextension/static/vendors-node_modules_toastr_toastr_js.39c3e89e462a0d392ed0.js.map
opensarlab_notifications/public/index.html
opensarlab_notifications-1.0.2.data/data/etc/jupyter/jupyter_notebook_config.d/opensarlab_notifications.json
opensarlab_notifications-1.0.2.data/data/etc/jupyter/jupyter_server_config.d/opensarlab_notifications.json
opensarlab_notifications-1.0.2.data/data/share/jupyter/labextensions/opensarlab-notifications/build_log.json
opensarlab_notifications-1.0.2.dist-info/LICENSE
opensarlab_notifications-1.0.2.dist-info/METADATA
opensarlab_notifications-1.0.2.dist-info/WHEEL
opensarlab_notifications-1.0.2.dist-info/top_level.txt
opensarlab_notifications-1.0.2.dist-info/RECORD
