Metadata-Version: 2.1
Name: opensarlab-notifications
Version: 1.0.2
Summary: A JupyterLab extension for OpenSARlab that provides notification popups.
Home-page: https://github.com/ASFOpenSARlab/opensarlab-extensions
Author: ASF OpenSARlab Team
Author-email: uaf-jupyterhub-asf@alaska.edu
License: BSD-3-Clause
Keywords: Jupyter,JupyterLab,JupyterLab3
Platform: Linux
Platform: Mac OS X
Platform: Windows
Classifier: License :: OSI Approved :: BSD License
Classifier: Programming Language :: Python
Classifier: Programming Language :: Python :: 3
Classifier: Programming Language :: Python :: 3.6
Classifier: Programming Language :: Python :: 3.7
Classifier: Programming Language :: Python :: 3.8
Classifier: Programming Language :: Python :: 3.9
Classifier: Framework :: Jupyter
Requires-Python: >=3.6
License-File: LICENSE
Requires-Dist: jupyter-server (<2,>=1.6)
Requires-Dist: ics (==0.7)
Requires-Dist: html2text
Requires-Dist: requests
Requires-Dist: pyyaml
